monki/__init__.py
monki/core.py
monki/enhancers.py
monki-0.1.1.dist-info/LICENSE
monki-0.1.1.dist-info/METADATA
monki-0.1.1.dist-info/WHEEL
monki-0.1.1.dist-info/top_level.txt
monki-0.1.1.dist-info/RECORD
