Metadata-Version: 2.1
Name: monki
Version: 0.1.1
Summary: Patch functions at runtime, the easy way.
Home-page: https://github.com/avivc/monki
Author: Aviv Cohn
Author-email: avivcohn1@gmail.com
License: MIT
Keywords: monkey patching utility programming development
Platform: UNKNOWN
Classifier: License :: OSI Approved :: MIT License
Classifier: Programming Language :: Python :: 3
Classifier: Programming Language :: Python :: 3.7
Classifier: Operating System :: OS Independent
